{
	"video_name": "mix_27_360p",
	"length": "00:03:23",
	"frame_num": "6114",
	"event": [
		{
			"event": "falldown",
			"start_time": "00:00:00",
			"end_time": "00:00:11",
			"start_frame": "1",
			"end_frame": "344",
			"origin_file_name": "cam5_falldown_3_1080p.mp4",
			"cam_id": "cam5"
		},
		{
			"event": "none",
			"start_time": "00:00:11",
			"end_time": "00:00:21",
			"start_frame": "345",
			"end_frame": "648",
			"origin_file_name": "cam2_none_1.mp4",
			"cam_id": "cam2"
		},
		{
			"event": "assault",
			"start_time": "00:00:21",
			"end_time": "00:00:51",
			"start_frame": "649",
			"end_frame": "1557",
			"origin_file_name": "assault_seyeon_16_1.mp4",
			"cam_id": "ives"
		},
		{
			"event": "none",
			"start_time": "00:00:51",
			"end_time": "00:01:02",
			"start_frame": "1558",
			"end_frame": "1864",
			"origin_file_name": "cam1_none_1.mp4",
			"cam_id": "cam1"
		},
		{
			"event": "tailing,wanderer",
			"start_time": "00:01:01",
			"end_time": "00:01:37",
			"start_frame": "1865",
			"end_frame": "2924",
			"origin_file_name": "cam3_tailing_10.mp4",
			"cam_id": "cam3"
		},
		{
			"event": "none",
			"start_time": "00:01:37",
			"end_time": "00:01:47",
			"start_frame": "2925",
			"end_frame": "3232",
			"origin_file_name": "cam5_none_1.mp4",
			"cam_id": "cam5"
		},
		{
			"event": "assault",
			"start_time": "00:01:47",
			"end_time": "00:02:18",
			"start_frame": "3233",
			"end_frame": "4141",
			"origin_file_name": "assault_seyeon_25_2.mp4",
			"cam_id": "ives"
		},
		{
			"event": "none",
			"start_time": "00:02:18",
			"end_time": "00:02:28",
			"start_frame": "4142",
			"end_frame": "4448",
			"origin_file_name": "cam3_none_1.mp4",
			"cam_id": "cam3"
		},
		{
			"event": "kidnapping,assault",
			"start_time": "00:02:28",
			"end_time": "00:02:43",
			"start_frame": "4449",
			"end_frame": "4904",
			"origin_file_name": "cam5_kidnapping_5.mp4",
			"cam_id": "cam5"
		},
		{
			"event": "none",
			"start_time": "00:02:43",
			"end_time": "00:02:53",
			"start_frame": "4905",
			"end_frame": "5208",
			"origin_file_name": "cam4_none_1.mp4",
			"cam_id": "cam4"
		},
		{
			"event": "wanderer",
			"start_time": "00:02:53",
			"end_time": "00:03:23",
			"start_frame": "5209",
			"end_frame": "6114",
			"origin_file_name": "cam3_wanderer_3.mp4",
			"cam_id": "cam3"
		}
	]
}